tgpt2/__init__.py
tgpt2/__main__.py
tgpt2/console.py
tgpt2/imager.py
tgpt2/tgpt2.py
tgpt2/utils.py
tgpt2-0.0.5.dist-info/LICENSE
tgpt2-0.0.5.dist-info/METADATA
tgpt2-0.0.5.dist-info/WHEEL
tgpt2-0.0.5.dist-info/entry_points.txt
tgpt2-0.0.5.dist-info/top_level.txt
tgpt2-0.0.5.dist-info/RECORD
