Metadata-Version: 2.1
Name: tgpt2
Version: 0.0.5
Summary: Interact with AI without API key
Home-page: https://github.com/Simatwa/python-tgpt
Author: Smartwa
Author-email: simatwacaleb@proton.me
Maintainer: Smartwa
License: MIT
Project-URL: Bug Report, https://github.com/Simatwa/python-tgpt/issues/new
Project-URL: Homepage, https://github.com/Simatwa/python-tgpt
Project-URL: Source Code, https://github.com/Simatwa/python-tgpt
Project-URL: Issue Tracker, https://github.com/Simatwa/python-tgpt/issues
Project-URL: Download, https://github.com/Simatwa/python-tgpt/releases
Project-URL: Documentation, https://github.com/Simatwa/python-tgpt/blob/main/docs
Keywords: chatgpt,gpt,chatgpt-cli,chatgpt-sdk,chatgpt-api,llama-api
Classifier: License :: OSI Approved :: MIT License
Classifier: Intended Audience :: Developers
Classifier: Intended Audience :: Developers
Classifier: Natural Language :: English
Classifier: License :: Free For Home Use
Classifier: Intended Audience :: Customer Service
Classifier: Programming Language :: Python
Classifier: Topic :: Software Development :: Libraries :: Python Modules
Classifier: Topic :: Scientific/Engineering :: Artificial Intelligence
Classifier: Programming Language :: Python :: 3 :: Only
Classifier: Programming Language :: Python :: 3.10
Classifier: Programming Language :: Python :: 3.10
Classifier: Programming Language :: Python :: 3.11
Classifier: Programming Language :: Python :: 3.12
Requires-Python: >=3.9
License-File: LICENSE
Requires-Dist: requests (==2.28.2)
Requires-Dist: click (==8.1.3)
Requires-Dist: rich (==13.3.4)
Requires-Dist: clipman (==3.1.0)
Requires-Dist: pyperclip (==1.8.2)
